[
  {
    "update_id": 501,
    "client_id": 101,
    "update_type": "WhatsApp",
    "old_status_no": 6,
    "new_status_no": 8,
    "request_type": "Document",
    "request_subtype": "Quotation",
    "note": "Client checked quotation and asked for bulk discount plus 3-day earlier delivery.",
    "followup_date": "2026-06-06",
    "followup_time": "11:30",
    "created_by": "Rohit",
    "created_at": "2026-06-06T09:20:00"
  },
  {
    "update_id": 502,
    "client_id": 101,
    "update_type": "Document Sent",
    "old_status_no": 5,
    "new_status_no": 6,
    "request_type": "Document",
    "request_subtype": "Quotation",
    "note": "Quotation PDF shared on WhatsApp after phone discussion.",
    "followup_date": "2026-06-06",
    "followup_time": "11:30",
    "created_by": "Rohit",
    "created_at": "2026-06-05T16:30:00"
  },
  {
    "update_id": 503,
    "client_id": 102,
    "update_type": "Document Sent",
    "old_status_no": 5,
    "new_status_no": 6,
    "request_type": "Document",
    "request_subtype": "Delivery",
    "note": "Catalogue and tentative delivery timeline sent on WhatsApp.",
    "followup_date": "2026-06-06",
    "followup_time": "16:30",
    "created_by": "Rohit",
    "created_at": "2026-06-05T16:30:00"
  },
  {
    "update_id": 504,
    "client_id": 103,
    "update_type": "Call",
    "old_status_no": 10,
    "new_status_no": 9,
    "request_type": "None",
    "request_subtype": "None",
    "note": "Client confirmed order but said advance will be transferred after accounts approval.",
    "followup_date": "2026-06-06",
    "followup_time": "14:00",
    "created_by": "Priya",
    "created_at": "2026-06-06T10:10:00"
  },
  {
    "update_id": 505,
    "client_id": 104,
    "update_type": "Follow-up",
    "old_status_no": 3,
    "new_status_no": 7,
    "request_type": "Information",
    "request_subtype": "Price",
    "note": "Client asked to call again after internal factory meeting.",
    "followup_date": "2026-06-05",
    "followup_time": "17:00",
    "created_by": "Suresh",
    "created_at": "2026-06-04T18:45:00"
  },
  {
    "update_id": 506,
    "client_id": 105,
    "update_type": "WhatsApp",
    "old_status_no": 9,
    "new_status_no": 10,
    "request_type": "Document",
    "request_subtype": "Receipt",
    "note": "Order confirmed on WhatsApp. Client requested invoice and receipt copy.",
    "followup_date": "2026-06-07",
    "followup_time": "10:00",
    "created_by": "Priya",
    "created_at": "2026-06-06T11:00:00"
  },
  {
    "update_id": 507,
    "client_id": 101,
    "update_type": "Follow-up",
    "old_status_no": 8,
    "new_status_no": 8,
    "request_type": "Document",
    "request_subtype": "Quotation",
    "note": "Client asked for bulk discount after checking quotation.",
    "followup_date": "2026-06-08",
    "followup_time": "12:00",
    "created_by": "Mobile POC",
    "created_at": "2026-06-06T16:09:43"
  },
  {
    "update_id": 508,
    "client_id": 101,
    "update_type": "Follow-up",
    "old_status_no": 8,
    "new_status_no": 8,
    "request_type": "Document",
    "request_subtype": "Quotation",
    "note": "Client asked for bulk discount after checking quotation.",
    "followup_date": "2026-06-08",
    "followup_time": "12:00",
    "created_by": "Flutter POC",
    "created_at": "2026-06-20T06:47:49"
  }
]
